ansar/command/ansar_command.py
ansar/command/ansar_group.py
ansar/create/__init__.py
ansar/create/binding.py
ansar/create/coding.py
ansar/create/concurrently.py
ansar/create/grouping.py
ansar/create/home.py
ansar/create/latching.py
ansar/create/lifecycle.py
ansar/create/locking.py
ansar/create/log.py
ansar/create/machine.py
ansar/create/object.py
ansar/create/pending.py
ansar/create/point.py
ansar/create/procedure.py
ansar/create/processing.py
ansar/create/properties.py
ansar/create/retry.py
ansar/create/rolling.py
ansar/create/root.py
ansar/create/space.py
ansar/create/storage.py
ansar/create/test.py
ansar/create/timing.py
ansar_create-1.0.50.dist-info/LICENSE
ansar_create-1.0.50.dist-info/METADATA
ansar_create-1.0.50.dist-info/WHEEL
ansar_create-1.0.50.dist-info/entry_points.txt
ansar_create-1.0.50.dist-info/top_level.txt
ansar_create-1.0.50.dist-info/RECORD
